reimport/__init__.py
reimport/_reimport.py
reimport_ng-1.5.1.dist-info/LICENSE
reimport_ng-1.5.1.dist-info/METADATA
reimport_ng-1.5.1.dist-info/WHEEL
reimport_ng-1.5.1.dist-info/top_level.txt
reimport_ng-1.5.1.dist-info/RECORD
