Metadata-Version: 2.1
Name: reimport_ng
Version: 1.5.1
Summary: Reimport a module in Python3
Author-email: grongier <guillaume.rongier@intersystems.com>
License: MIT License
Project-URL: homepage, https://github.com/grongierisc/reimport-ng
Project-URL: documentation, https://github.com/grongierisc/reimport-ng/blob/master/README.md
Project-URL: repository, https://github.com/grongierisc/reimport-ng
Project-URL: issues, https://github.com/grongierisc/reimport-ng/issues
Keywords: reimport,module,python3
Classifier: Development Status :: 5 - Production/Stable
Classifier: Intended Audience :: Developers
Classifier: License :: OSI Approved :: MIT License
Classifier: Operating System :: OS Independent
Classifier: Programming Language :: Python :: 3.6
Classifier: Programming Language :: Python :: 3.7
Classifier: Programming Language :: Python :: 3.8
Classifier: Programming Language :: Python :: 3.9
Classifier: Programming Language :: Python :: 3.10
Classifier: Programming Language :: Python :: 3.11
Classifier: Topic :: Utilities
License-File: LICENSE
